Metadata-Version: 1.0
Name: django-shop-simplenotifications
Version: 0.1.4
Summary: A simple reusable app for django-shop that sends emailnotifications on certain events
Home-page: https://github.com/bitmazk/django-shop-simplenotifications
Author: Martin Brochhaus
Author-email: martin.brochhaus@gmail.com
License: BSD License
Keywords: django,django-shop,email,notifications
Platform: OS Independent
Classifier: Development Status :: 3 - Alpha
Classifier: Environment :: Web Environment
Classifier: Framework :: Django
Classifier: Intended Audience :: Developers
Classifier: License :: OSI Approved :: BSD License
Classifier: Operating System :: OS Independent
Classifier: Programming Language :: Python
Classifier: Topic :: Communications :: Email
Classifier: Topic :: Software Development
Classifier: Topic :: Software Development :: Libraries :: Python Modules
